{
    "BaseModel.64822363-4982-4dba-99e2-9366ed858e3c": {
        "id": "64822363-4982-4dba-99e2-9366ed858e3c",
        "created_at": "2022-02-06T05:29:49.282298",
        "updated_at": "2022-02-06T05:29:49.282403",
        "__class__": "BaseModel"
    },
    "State.040f8c0e-3b93-42c6-944b-c20fe27919fe": {
        "id": "040f8c0e-3b93-42c6-944b-c20fe27919fe",
        "created_at": "2022-02-06T21:35:07.533724",
        "updated_at": "2022-02-06T21:35:07.533770",
        "__class__": "State"
    },
    "State.53326fa2-39c2-47e9-bc91-613cddd936ad": {
        "id": "53326fa2-39c2-47e9-bc91-613cddd936ad",
        "created_at": "2022-02-06T21:36:24.123457",
        "updated_at": "2022-02-06T21:36:24.123504",
        "__class__": "State"
    },
    "State.15fc809e-6d4f-4ab1-bec0-3dea0ad95ca5": {
        "id": "15fc809e-6d4f-4ab1-bec0-3dea0ad95ca5",
        "created_at": "2022-02-06T21:36:28.848386",
        "updated_at": "2022-02-06T21:36:28.849010",
        "__class__": "State"
    }
}
